datasets/__init__.py
datasets/coco.py
datasets/coco_eval.py
datasets/coco_panoptic.py
datasets/panoptic_eval.py
datasets/transforms.py
models/__init__.py
models/backbone.py
models/detr.py
models/matcher.py
models/position_encoding.py
models/segmentation.py
models/transformer.py
util/__init__.py
util/box_ops.py
util/misc.py
util/plot_utils.py
detr-0.1.4.dist-info/LICENSE
detr-0.1.4.dist-info/METADATA
detr-0.1.4.dist-info/WHEEL
detr-0.1.4.dist-info/namespace_packages.txt
detr-0.1.4.dist-info/top_level.txt
detr-0.1.4.dist-info/RECORD
